{"Infos":{"ID":370816,"Pseudo":"ana-raiga8","Created_at":"2017-09-12T14:45:14+02:00","Updated_at":"2017-09-25T05:22:02+02:00","Cheked_profil":1,"Pays":"France","Nb_messages":0,"Img_lien":"http://image.jeuxvideo.com/avatar-md/default.jpg","Nb_relation":0,"Banni":1,"Date_inscription":"1980-01-01T00:00:00+01:00","Coord_X":0,"Coord_Y":0},"AnalyseTextuel":[{"Word":"ivanovic","Nb":1},{"Word":"chance","Nb":1},{"Word":"ana","Nb":1}],"SujetByYear":[{"Label":"2017","Nb":0},{"Label":"2016","Nb":0},{"Label":"2015","Nb":1},{"Label":"2014","Nb":0},{"Label":"2013","Nb":0},{"Label":"2012","Nb":0},{"Label":"2011","Nb":0},{"Label":"2010","Nb":0},{"Label":"2009","Nb":0},{"Label":"2008","Nb":0},{"Label":"2007","Nb":0},{"Label":"2006","Nb":0},{"Label":"2005","Nb":0},{"Label":"2004","Nb":0}],"SujetByLastMouth":[{"Label":"2017-Jui","Nb":0},{"Label":"2017-Mai","Nb":0},{"Label":"2017-Fev","Nb":0},{"Label":"2017-Jan","Nb":0},{"Label":"2016-Dec","Nb":0},{"Label":"2016-Nov","Nb":0},{"Label":"2017-Sep","Nb":0},{"Label":"2017-Aou","Nb":0},{"Label":"2017-Avr","Nb":0},{"Label":"2017-Mar","Nb":0},{"Label":"2017-Oct","Nb":0},{"Label":"2017-Juin","Nb":0}],"Sujets":[{"ID":6272455,"Created_at":"2017-09-12T14:45:14+02:00","Updated_at":"2017-09-12T14:45:14+02:00","Parcoured":0,"Url":"http://www.jeuxvideo.com/forums/42-51-41077797-1-0-1-0-j-ai-des-chance-de-me-faire-ana-ivanovic.htm","Title":"inconnu","Auteur":370816,"Nb_reponses":1,"Initialised_at":"2015-09-15T00:00:00+02:00"}],"Similaires":[{"S":"ana-raiga8","Dist":1},{"S":"ana-raiga08","Dist":0.9696969696969697},{"S":"ana-raigaP","Dist":0.9333333333333332},{"S":"ana-raigaOL","Dist":0.9060606060606061},{"S":"ana-raiga91","Dist":0.9060606060606061},{"S":"ana-raiga02","Dist":0.9060606060606061},{"S":"ana-raigaBBC","Dist":0.8833333333333333},{"S":"ana-raigaB21","Dist":0.8833333333333333},{"S":"ana-raigaLDC","Dist":0.8833333333333333},{"S":"ana-raigareal","Dist":0.8641025641025641},{"S":"Ana-raiga","Dist":0.8546296296296297},{"S":"ana-lyonraiga","Dist":0.7900284900284901},{"S":"Ana-raigaB20","Dist":0.7805555555555556},{"S":"anaamir","Dist":0.7634920634920634},{"S":"Ana-raigaKICk","Dist":0.7634615384615385},{"S":"Ana-raigafekir","Dist":0.7488095238095238},{"S":"ana-nas","Dist":0.7380952380952381},{"S":"an-dreiia","Dist":0.7000000000000001},{"S":"anagal","Dist":0.6888888888888888},{"S":"anais8","Dist":0.6888888888888888},{"S":"anacin","Dist":0.6888888888888888},{"S":"anagram47","Dist":0.6851851851851851},{"S":"Ana-","Dist":0.6833333333333332},{"S":"anahnatani","Dist":0.6777777777777777},{"S":"anacristin","Dist":0.6666666666666666},{"S":"anaisco","Dist":0.6571428571428571},{"S":"anaenta","Dist":0.6571428571428571},{"S":"an-angry-bird","Dist":0.6509157509157509},{"S":"anaisg95","Dist":0.6416666666666667},{"S":"Ana-vars","Dist":0.6416666666666667}]}