{"Infos":{"ID":214810,"Pseudo":"an-dreiia","Created_at":"2017-09-09T03:51:00+02:00","Updated_at":"2017-09-24T14:17:50+02:00","Cheked_profil":1,"Pays":"France","Nb_messages":1,"Img_lien":"http://image.jeuxvideo.com/avatar-md/default.jpg","Nb_relation":0,"Banni":0,"Date_inscription":"2008-12-27T00:00:00+01:00","Coord_X":0,"Coord_Y":0},"AnalyseTextuel":[{"Word":"ordi","Nb":1},{"Word":"portable","Nb":1},{"Word":"sims","Nb":1}],"SujetByYear":[{"Label":"2017","Nb":0},{"Label":"2016","Nb":0},{"Label":"2015","Nb":0},{"Label":"2014","Nb":0},{"Label":"2013","Nb":0},{"Label":"2012","Nb":0},{"Label":"2011","Nb":0},{"Label":"2010","Nb":0},{"Label":"2009","Nb":0},{"Label":"2008","Nb":1},{"Label":"2007","Nb":0},{"Label":"2006","Nb":0},{"Label":"2005","Nb":0},{"Label":"2004","Nb":0}],"SujetByLastMouth":[{"Label":"2017-Aou","Nb":0},{"Label":"2017-Mar","Nb":0},{"Label":"2017-Fev","Nb":0},{"Label":"2017-Jan","Nb":0},{"Label":"2016-Dec","Nb":0},{"Label":"2016-Nov","Nb":0},{"Label":"2017-Sep","Nb":0},{"Label":"2017-Jui","Nb":0},{"Label":"2017-Juin","Nb":0},{"Label":"2017-Mai","Nb":0},{"Label":"2017-Avr","Nb":0},{"Label":"2017-Oct","Nb":0}],"Sujets":[{"ID":3179573,"Created_at":"2017-09-09T03:51:00+02:00","Updated_at":"2017-09-09T03:51:00+02:00","Parcoured":0,"Url":"http://www.jeuxvideo.com/forums/1-51-5366217-1-0-1-0-sims-ordi-portable.htm","Title":"inconnu","Auteur":214810,"Nb_reponses":1,"Initialised_at":"2008-12-27T00:00:00+01:00"}],"Similaires":[{"S":"an-dreiia","Dist":1},{"S":"Ana-raigafekir","Dist":0.7367724867724869},{"S":"Ana-raiga","Dist":0.7222222222222222},{"S":"ana-raiga8","Dist":0.7000000000000001},{"S":"ana-raigaP","Dist":0.7000000000000001},{"S":"anais-destin","Dist":0.6917989417989419},{"S":"ana-raigaOL","Dist":0.6818181818181818},{"S":"ana-raiga91","Dist":0.6818181818181818},{"S":"ana-raiga02","Dist":0.6818181818181818},{"S":"ana-raiga08","Dist":0.6818181818181818},{"S":"an-gabe","Dist":0.671957671957672},{"S":"ana-raigaB21","Dist":0.6666666666666666},{"S":"Ana-raigaB20","Dist":0.6666666666666666},{"S":"ana-raigaLDC","Dist":0.6666666666666666},{"S":"ana-raigaBBC","Dist":0.6666666666666666},{"S":"Ana-raigaKICk","Dist":0.6538461538461539},{"S":"ana-raigareal","Dist":0.6538461538461539},{"S":"anaiogie","Dist":0.6481481481481481},{"S":"Anadraps","Dist":0.6481481481481481},{"S":"an-us","Dist":0.6444444444444445},{"S":"Anacroniik","Dist":0.6185185185185186},{"S":"Anagrammes","Dist":0.6185185185185186},{"S":"anacristin","Dist":0.6185185185185186},{"S":"anadiplose","Dist":0.6148148148148148},{"S":"An-Nur","Dist":0.611111111111111},{"S":"anael2","Dist":0.611111111111111},{"S":"anacin","Dist":0.611111111111111},{"S":"An7tre","Dist":0.611111111111111},{"S":"Anacardiaceae","Dist":0.5982905982905983},{"S":"ana-lyonraiga","Dist":0.5982905982905983}]}